hanzidentifier.py
hanzidentifier_preview-1.1.0.dist-info/LICENSE.txt
hanzidentifier_preview-1.1.0.dist-info/METADATA
hanzidentifier_preview-1.1.0.dist-info/WHEEL
hanzidentifier_preview-1.1.0.dist-info/top_level.txt
hanzidentifier_preview-1.1.0.dist-info/RECORD
