Metadata-Version: 2.1
Name: hanzidentifier-preview
Version: 1.1.0
Summary: Python module that identifies Chinese text as Simplified or Traditional.
Home-page: https://github.com/tsroten/hanzidentifier
Author: Thomas Roten
Author-email: thomas@roten.us
License: UNKNOWN
Keywords: chinese,mandarin,hanzi,characters,simplified,traditional,identify,identification,cjk
Platform: any
Classifier: Programming Language :: Python
Classifier: Topic :: Software Development :: Libraries :: Python Modules
Classifier: License :: OSI Approved :: MIT License
Classifier: Operating System :: OS Independent
Classifier: Intended Audience :: Developers
Classifier: Programming Language :: Python :: 2.7
Classifier: Programming Language :: Python :: 3
Classifier: Programming Language :: Python :: 3.3
Classifier: Programming Language :: Python :: 3.4
Classifier: Topic :: Text Processing :: Linguistic
Requires-Dist: zhon (>=1.1.3)
